fusionpbx_pilot/__init__.py
fusionpbx_pilot/page_objects/__init__.py
fusionpbx_pilot/page_objects/fusionpbx.py
fusionpbx_pilot/page_objects/page_objects.py
fusionpbx_pilot/page_objects/apps/__init__.py
fusionpbx_pilot/page_objects/apps/extension.py
fusionpbx_pilot/page_objects/apps/extensions.py
fusionpbx_pilot/page_objects/core/__init__.py
fusionpbx_pilot/page_objects/core/domain.py
fusionpbx_pilot/page_objects/core/domains.py
fusionpbx_pilot/page_objects/core/user.py
fusionpbx_pilot-0.2.2.dist-info/licenses/LICENSE
fusionpbx_pilot-0.2.2.dist-info/METADATA
fusionpbx_pilot-0.2.2.dist-info/WHEEL
fusionpbx_pilot-0.2.2.dist-info/top_level.txt
fusionpbx_pilot-0.2.2.dist-info/RECORD
