Metadata-Version: 2.4
Name: fusionpbx_pilot
Version: 0.2.2
Summary: Python client LIB for FusionPBX
Author-email: Marcelo Araujo <marcelo@gnovit.com>
License-Expression: GPL-3.0-or-later
Project-URL: Homepage, https://github.com/gnovit/fusionpbx-pilot
Project-URL: Issues, https://github.com/gnovit/fusionpbx-pilot/issues
Keywords: fusionpbx,telephony,voip,python,client-library,communication,sip,automation
Classifier: Programming Language :: Python :: 3
Classifier: Operating System :: OS Independent
Classifier: Intended Audience :: Developers
Classifier: Topic :: Software Development :: Libraries
Classifier: Topic :: Communications :: Telephony
Classifier: Development Status :: 4 - Beta
Requires-Python: >=3.10
License-File: LICENSE
Requires-Dist: attrs>=25.3.0
Requires-Dist: certifi>=2025.1.31
Requires-Dist: h11>=0.14.0
Requires-Dist: idna>=3.10
Requires-Dist: outcome>=1.3.0.post0
Requires-Dist: pysocks>=1.7.1
Requires-Dist: selenium>=4.31.0
Requires-Dist: sniffio>=1.3.1
Requires-Dist: sortedcontainers>=2.4.0
Requires-Dist: trio>=0.29.0
Requires-Dist: trio-websocket>=0.12.2
Requires-Dist: typing-extensions>=4.13.1
Requires-Dist: urllib3>=2.3.0
Requires-Dist: wsproto>=1.2.0
Dynamic: license-file
